Metadata-Version: 2.1
Name: ns3vc
Version: 1.0.0
Summary: Unofficial pip package for Amphion's NaturalSpeech3 implementation
Home-page: https://github.com/ml-for-speech/ns3vc
Author: ml-for-speech, mrfakename
License-File: LICENSE
Requires-Dist: numpy
Requires-Dist: librosa
Requires-Dist: matplotlib
Requires-Dist: tqdm
Requires-Dist: hydra-core
Requires-Dist: torch
Requires-Dist: torchvision
Requires-Dist: torchaudio
Requires-Dist: tensorboard
Requires-Dist: onnxruntime
Requires-Dist: onnx
Requires-Dist: pyworld
Requires-Dist: pesq
Requires-Dist: pystoi
Requires-Dist: gradio
Requires-Dist: einops
Requires-Dist: PyWavelets
Requires-Dist: cached_path
